odoo9_addon_runbot_travis2docker-9.0.1.1.0-py2.7-nspkg.pth
odoo_addons/runbot_travis2docker/__openerp__.py
odoo_addons/runbot_travis2docker/__init__.py
odoo_addons/runbot_travis2docker/README.rst
odoo_addons/runbot_travis2docker/models/runbot_build.py
odoo_addons/runbot_travis2docker/models/__init__.py
odoo_addons/runbot_travis2docker/models/runbot_repo.py
odoo_addons/runbot_travis2docker/views/runbot_repo_view.xml
odoo_addons/runbot_travis2docker/tests/test_runbot_build.py
odoo_addons/runbot_travis2docker/tests/__init__.py
odoo_addons/runbot_travis2docker/demo/runbot_repo_demo.xml
odoo9_addon_runbot_travis2docker-9.0.1.1.0.dist-info/top_level.txt
odoo9_addon_runbot_travis2docker-9.0.1.1.0.dist-info/WHEEL
odoo9_addon_runbot_travis2docker-9.0.1.1.0.dist-info/RECORD
odoo9_addon_runbot_travis2docker-9.0.1.1.0.dist-info/metadata.json
odoo9_addon_runbot_travis2docker-9.0.1.1.0.dist-info/DESCRIPTION.rst
odoo9_addon_runbot_travis2docker-9.0.1.1.0.dist-info/METADATA
odoo9_addon_runbot_travis2docker-9.0.1.1.0.dist-info/namespace_packages.txt
