Metadata-Version: 2.0
Name: odoo9-addon-runbot-travis2docker
Version: 9.0.1.1.0
Summary: Generate docker with odoo instance based on .travis.yml
Home-page: https://odoo-community.org/
Author: UNKNOWN
Author-email: UNKNOWN
License: AGPL-3
Platform: UNKNOWN
Requires-Dist: odoo (<9.1a,>=9.0a)
Requires-Dist: odoo9-addon-runbot
Requires-Dist: travis2docker
Classifier: Programming Language :: Python :: 2.7
Classifier: Framework :: Odoo
Classifier: License :: OSI Approved :: GNU Affero General Public License v3
